server.py
ping_htdy_server-0.1.1.dist-info/METADATA
ping_htdy_server-0.1.1.dist-info/WHEEL
ping_htdy_server-0.1.1.dist-info/entry_points.txt
ping_htdy_server-0.1.1.dist-info/top_level.txt
ping_htdy_server-0.1.1.dist-info/RECORD
