Metadata-Version: 2.4
Name: ping-htdy-server
Version: 0.1.1
Summary: A simple tool to ping htdywmsxyz.zaza.eu.org
Author-email: kagty1 <726711238@qq.com>
License: MIT
Classifier: Programming Language :: Python :: 3
Classifier: License :: OSI Approved :: MIT License
Classifier: Operating System :: OS Independent
Requires-Python: >=3.6
